mmv_playground/__init__.py
mmv_playground/_widget.py
mmv_playground/napari.yaml
mmv_playground/_tests/__init__.py
mmv_playground/_tests/test_widget.py
MMV_playground-0.1.4.dist-info/LICENSE
MMV_playground-0.1.4.dist-info/METADATA
MMV_playground-0.1.4.dist-info/WHEEL
MMV_playground-0.1.4.dist-info/entry_points.txt
MMV_playground-0.1.4.dist-info/top_level.txt
MMV_playground-0.1.4.dist-info/RECORD
