Metadata-Version: 2.2
Name: MMV-playground
Version: 0.1.4
Summary: Napari plugin for 2D microscopy segmentation
Author: Peter Lampen
Author-email: lampen@isas.de
License: 
Project-URL: Bug Tracker, https://github.com/MMV-Lab/MMV-playground/issues
Project-URL: Documentation, https://github.com/MMV-Lab/MMV-playground#README.md
Project-URL: Source Code, https://github.com/MMV-Lab/MMV-playground
Project-URL: User Support, https://github.com/MMV-Lab/MMV-playground/issues
Classifier: Development Status :: 2 - Pre-Alpha
Classifier: Framework :: napari
Classifier: Intended Audience :: Developers
Classifier: License :: OSI Approved :: BSD License
Classifier: Operating System :: OS Independent
Classifier: Programming Language :: Python
Classifier: Programming Language :: Python :: 3
Classifier: Programming Language :: Python :: 3 :: Only
Classifier: Programming Language :: Python :: 3.9
Classifier: Programming Language :: Python :: 3.10
Classifier: Programming Language :: Python :: 3.11
Classifier: Programming Language :: Python :: 3.12
Classifier: Topic :: Scientific/Engineering :: Image Processing
Requires-Python: >=3.9
License-File: LICENSE
Requires-Dist: aicssegmentation
Requires-Dist: itk
Requires-Dist: napari
Requires-Dist: numpy
Requires-Dist: qtpy
Requires-Dist: scikit-image
Requires-Dist: scipy
Provides-Extra: testing
Requires-Dist: tox; extra == "testing"
Requires-Dist: pytest; extra == "testing"
Requires-Dist: pytest-cov; extra == "testing"
Requires-Dist: pytest-qt; extra == "testing"
Requires-Dist: napari; extra == "testing"
Requires-Dist: pyqt5; extra == "testing"
